kev_checker/__init__.py
kev_checker-0.1.0.dist-info/LICENSE
kev_checker-0.1.0.dist-info/METADATA
kev_checker-0.1.0.dist-info/WHEEL
kev_checker-0.1.0.dist-info/entry_points.txt
kev_checker-0.1.0.dist-info/top_level.txt
kev_checker-0.1.0.dist-info/RECORD
