Metadata-Version: 2.1
Name: kev-checker
Version: 0.1.0
Summary: A basic Python program to check Cybersecurity & Infrastructure Security Agency (CISA) Known Exploited Vulnerabilities (KEV) Catalog
Author: Omar Santos, Charles Ezell III
License: BSD-2-Clause
Keywords: CISA,CVE,Known Exploited Vulnerabilities,KEV,Vulnerabilities
Classifier: License :: OSI Approved :: BSD License
Classifier: Programming Language :: Python :: 3
Requires-Python: >=3.7
License-File: LICENSE
Requires-Dist: argparse
Requires-Dist: pandas
Requires-Dist: requests
